{"cameraMode":{"drawMode":0,"name":"Shaded","section":"Shading Mode"},"sceneLighting":true,"audioPlay":false,"sceneViewState":{"showFog":true,"showMaterialUpdate":false,"showSkybox":true,"showFlares":true,"showImageEffects":true,"showParticleSystems":true,"showVisualEffectGraphs":true,"m_FxEnabled":true},"in2DMode":false,"pivot":{"x":206.6861572265625,"y":287.29443359375,"z":230.7357177734375},"rotation":{"x":0.06209065020084381,"y":-0.9166864156723023,"z":0.15717655420303346,"w":0.36214151978492739},"size":680.7313232421875,"orthographic":false}